mail_notification/__init__.py
mail_notification/connection.py
mouritech_mail_notification-0.0.2.dist-info/LICENSE.txt
mouritech_mail_notification-0.0.2.dist-info/METADATA
mouritech_mail_notification-0.0.2.dist-info/WHEEL
mouritech_mail_notification-0.0.2.dist-info/top_level.txt
mouritech_mail_notification-0.0.2.dist-info/RECORD
