Metadata-Version: 2.1
Name: mouritech-mail-notification
Version: 0.0.2
Summary: Sending mails
Home-page: https://gitlab.mouritech.com/mt-digital-core-platform/python/mail-notification
Author: Venkatesh Areti
Author-email: venkateshar.in@mouritech.com
License: MIT
Project-URL: Source, https://gitlab.mouritech.com/mt-digital-core-platform/python/mail-notification
Platform: UNKNOWN
Classifier: Intended Audience :: Developers
Classifier: Topic :: Utilities
Classifier: License :: OSI Approved :: MIT License
Classifier: Programming Language :: Python :: 3
Requires-Python: >=3
Provides-Extra: dev
